{"name":"Anand Tyagi","tagline":"Welcome to my Page!","body":"### About me:\r\nI've always been interested in introspecting myself and hence I've found so many traits so far. Here are they:\r\n```\r\nDreamer || agnostic || ethical || introvert || asocial || pragmatic || ambitious || over-sensitive observer || mediocre programmer || great procrastinator || bibliophile || feminist || wanna-be entrepreneur+philanthropist and rest of me is still being unfolded...\r\n```\r\n\r\n### My education:\r\nI'm a Computer Science undergraduate in Uttar Pradesh Technical University. I'm pursuing it since 2012 and expecting to finish by 2016.\r\n\r\n### My resume:\r\nHere is a link to my resume: \r\n\r\n### Contact Information:\r\nEmail: anandtyagi77@yahoo.in\r\nQuora: http://www.quora.com/Anand-Tyagi-1\r\nGithub profile: https://github.com/andynrkri\r\n\r\n### Thank you for visiting my page. Have a great time ahead.","google":"","note":"Don't delete this file! It's used internally to help with page regeneration."}